{
  "coverage": "98.3%",
  "expectCount": 59,
  "actualCount": 58,
  "files": {
    "src/Cloneable.js": {
      "expectCount": 4,
      "actualCount": 4,
      "undocumentLines": []
    },
    "src/Cloner.js": {
      "expectCount": 18,
      "actualCount": 18,
      "undocumentLines": []
    },
    "src/Color.js": {
      "expectCount": 11,
      "actualCount": 10,
      "undocumentLines": [
        178
      ]
    },
    "src/Event.js": {
      "expectCount": 5,
      "actualCount": 5,
      "undocumentLines": []
    },
    "src/EventManager.js": {
      "expectCount": 6,
      "actualCount": 6,
      "undocumentLines": []
    },
    "src/Extensible.js": {
      "expectCount": 4,
      "actualCount": 4,
      "undocumentLines": []
    },
    "src/IDGenerator.js": {
      "expectCount": 5,
      "actualCount": 5,
      "undocumentLines": []
    },
    "src/Observable.js": {
      "expectCount": 3,
      "actualCount": 3,
      "undocumentLines": []
    },
    "src/Plugin.js": {
      "expectCount": 3,
      "actualCount": 3,
      "undocumentLines": []
    }
  }
}